lzlab_blogs/__init__.py
lzlab_blogs/admin.py
lzlab_blogs/apps.py
lzlab_blogs/models.py
lzlab_blogs/tests.py
lzlab_blogs/urls.py
lzlab_blogs/views.py
lzlab_blogs/extensions/__init__.py
lzlab_blogs/extensions/mdeditor/__init__.py
lzlab_blogs/extensions/mdeditor/configs.py
lzlab_blogs/extensions/mdeditor/fields.py
lzlab_blogs/extensions/mdeditor/urls.py
lzlab_blogs/extensions/mdeditor/views.py
lzlab_blogs/extensions/mdeditor/widgets.py
lzlab_blogs/extensions/mdeditor/static/mdeditor/css/editormd.css
lzlab_blogs/extensions/mdeditor/static/mdeditor/css/editormd.logo.css
lzlab_blogs/extensions/mdeditor/static/mdeditor/css/editormd.logo.min.css
lzlab_blogs/extensions/mdeditor/static/mdeditor/css/editormd.min.css
lzlab_blogs/extensions/mdeditor/static/mdeditor/css/editormd.preview.css
lzlab_blogs/extensions/mdeditor/static/mdeditor/css/editormd.preview.min.css
lzlab_blogs/extensions/mdeditor/static/mdeditor/css/style.css
lzlab_blogs/extensions/mdeditor/static/mdeditor/fonts/FontAwesome.otf
lzlab_blogs/extensions/mdeditor/static/mdeditor/fonts/editormd-logo.eot
lzlab_blogs/extensions/mdeditor/static/mdeditor/fonts/editormd-logo.svg
lzlab_blogs/extensions/mdeditor/static/mdeditor/fonts/editormd-logo.ttf
lzlab_blogs/extensions/mdeditor/static/mdeditor/fonts/editormd-logo.woff
lzlab_blogs/extensions/mdeditor/static/mdeditor/fonts/fontawesome-webfont.eot
lzlab_blogs/extensions/mdeditor/static/mdeditor/fonts/fontawesome-webfont.svg
lzlab_blogs/extensions/mdeditor/static/mdeditor/fonts/fontawesome-webfont.ttf
lzlab_blogs/extensions/mdeditor/static/mdeditor/fonts/fontawesome-webfont.woff
lzlab_blogs/extensions/mdeditor/static/mdeditor/fonts/fontawesome-webfont.woff2
lzlab_blogs/extensions/mdeditor/static/mdeditor/images/loading.gif
lzlab_blogs/extensions/mdeditor/static/mdeditor/images/loading@2x.gif
lzlab_blogs/extensions/mdeditor/static/mdeditor/images/loading@3x.gif
lzlab_blogs/extensions/mdeditor/static/mdeditor/images/logos/editormd-favicon-16x16.ico
lzlab_blogs-0.0.4.dist-info/AUTHORS
lzlab_blogs-0.0.4.dist-info/METADATA
lzlab_blogs-0.0.4.dist-info/WHEEL
lzlab_blogs-0.0.4.dist-info/entry_points.txt
lzlab_blogs-0.0.4.dist-info/pbr.json
lzlab_blogs-0.0.4.dist-info/top_level.txt
lzlab_blogs-0.0.4.dist-info/RECORD
