Metadata-Version: 2.1
Name: lzlab-blogs
Version: 0.0.4
Summary: awsome project created by pycman.
Home-page: http://example.com
Author: singein
Author-email: singein@outlook.com
License: MIT
Platform: UNKNOWN
Requires-Dist: DjangoAppCenter (>=0.3.3)
Requires-Dist: Django
Requires-Dist: pypinyin
